ssm_parameter_store_cc/__init__.py
ssm_parameter_store_cc/stores.py
ssm_parameter_store_cc/version.py
ssm_parameter_store_cc-0.1.2.dist-info/licenses/LICENSE
ssm_parameter_store_cc-0.1.2.dist-info/METADATA
ssm_parameter_store_cc-0.1.2.dist-info/WHEEL
ssm_parameter_store_cc-0.1.2.dist-info/top_level.txt
ssm_parameter_store_cc-0.1.2.dist-info/RECORD
