Metadata-Version: 2.4
Name: ssm-parameter-store-cc
Version: 0.1.2
Summary: Simple Python wrapper for getting values from AWS Systems Manager Parameter Store-fork
Home-page: https://github.com/binaryCrossEntropy/ssm-parameter-store-cc
Author: Iqbal Singh
Author-email: iqbalamo93@gmail.com
License: MIT
Requires-Python: >=3.10
License-File: LICENSE
Requires-Dist: boto3
Dynamic: author
Dynamic: author-email
Dynamic: description
Dynamic: description-content-type
Dynamic: home-page
Dynamic: license
Dynamic: license-file
Dynamic: requires-dist
Dynamic: requires-python
Dynamic: summary
